PytorchZhongwenGuanfangJiaocheng17ChuyiFix1/README.md
PytorchZhongwenGuanfangJiaocheng17ChuyiFix1/__init__.py
PytorchZhongwenGuanfangJiaocheng17ChuyiFix1/__main__.py
PytorchZhongwenGuanfangJiaocheng17ChuyiFix1/file.epub
PytorchZhongwenGuanfangJiaocheng17ChuyiFix1/index.html
PytorchZhongwenGuanfangJiaocheng17ChuyiFix1/css/__init__.py
PytorchZhongwenGuanfangJiaocheng17ChuyiFix1/css/annotations.css
PytorchZhongwenGuanfangJiaocheng17ChuyiFix1/css/main.css
PytorchZhongwenGuanfangJiaocheng17ChuyiFix1/css/normalize.css
PytorchZhongwenGuanfangJiaocheng17ChuyiFix1/css/popup.css
PytorchZhongwenGuanfangJiaocheng17ChuyiFix1/font/__init__.py
PytorchZhongwenGuanfangJiaocheng17ChuyiFix1/font/fontello.eot
PytorchZhongwenGuanfangJiaocheng17ChuyiFix1/font/fontello.svg
PytorchZhongwenGuanfangJiaocheng17ChuyiFix1/font/fontello.ttf
PytorchZhongwenGuanfangJiaocheng17ChuyiFix1/font/fontello.woff
PytorchZhongwenGuanfangJiaocheng17ChuyiFix1/img/__init__.py
PytorchZhongwenGuanfangJiaocheng17ChuyiFix1/img/annotator-glyph-sprite.png
PytorchZhongwenGuanfangJiaocheng17ChuyiFix1/img/annotator-icon-sprite.png
PytorchZhongwenGuanfangJiaocheng17ChuyiFix1/img/apple-touch-icon.png
PytorchZhongwenGuanfangJiaocheng17ChuyiFix1/img/cancelfullscreen.png
PytorchZhongwenGuanfangJiaocheng17ChuyiFix1/img/close.png
PytorchZhongwenGuanfangJiaocheng17ChuyiFix1/img/fullscreen.png
PytorchZhongwenGuanfangJiaocheng17ChuyiFix1/img/loader.gif
PytorchZhongwenGuanfangJiaocheng17ChuyiFix1/img/menu-icon.png
PytorchZhongwenGuanfangJiaocheng17ChuyiFix1/img/save.png
PytorchZhongwenGuanfangJiaocheng17ChuyiFix1/img/saved.png
PytorchZhongwenGuanfangJiaocheng17ChuyiFix1/img/settings-s.png
PytorchZhongwenGuanfangJiaocheng17ChuyiFix1/img/settings.png
PytorchZhongwenGuanfangJiaocheng17ChuyiFix1/img/star.png
PytorchZhongwenGuanfangJiaocheng17ChuyiFix1/js/__init__.py
PytorchZhongwenGuanfangJiaocheng17ChuyiFix1/js/epub.js
PytorchZhongwenGuanfangJiaocheng17ChuyiFix1/js/epub.min.js
pytorch_zhongwen_guanfang_jiaocheng_1_7_chuyi_fix1-2025.3.25.0.dist-info/METADATA
pytorch_zhongwen_guanfang_jiaocheng_1_7_chuyi_fix1-2025.3.25.0.dist-info/WHEEL
pytorch_zhongwen_guanfang_jiaocheng_1_7_chuyi_fix1-2025.3.25.0.dist-info/entry_points.txt
pytorch_zhongwen_guanfang_jiaocheng_1_7_chuyi_fix1-2025.3.25.0.dist-info/top_level.txt
pytorch_zhongwen_guanfang_jiaocheng_1_7_chuyi_fix1-2025.3.25.0.dist-info/RECORD
